glocate-1.4.2.dist-info/metadata.json
glocate-1.4.2.dist-info/entry_points.txt
glocate-1.4.2.dist-info/DESCRIPTION.rst
glocate-1.4.2.dist-info/METADATA
glocate-1.4.2.dist-info/WHEEL
glocate-1.4.2.dist-info/RECORD
glocate-1.4.2.dist-info/top_level.txt
geolocate/__main__.py
geolocate/__init__.py
geolocate/glocate.py
geolocate/classes/system.py
geolocate/classes/parser.py
geolocate/classes/geowrapper.py
geolocate/classes/__init__.py
geolocate/classes/arguments.py
geolocate/classes/exceptions.py
geolocate/classes/config.py
