Metadata-Version: 2.0
Name: glocate
Version: 1.4.2
Summary: This program scans given text to find urls and IP addresses. The output is the same text but every url and IP address is going to have its geolocation data appended.
Home-page: https://github.com/dante-signal31/geolocate
Author: Dante Signal31
Author-email: dante.signal31@gmail.com
License: BSD-3
Download-URL: https://github.com/dante-signal31/geolocate/releases
Keywords: geolocation ip addresses
Platform: UNKNOWN
Classifier: Development Status :: 4 - Beta
Classifier: Intended Audience :: Developers
Classifier: Intended Audience :: Information Technology
Classifier: Intended Audience :: Science/Research
Classifier: Intended Audience :: System Administrators
Classifier: Intended Audience :: Telecommunications Industry
Classifier: Intended Audience :: Other Audience
Classifier: Topic :: System :: Networking
Classifier: Topic :: Security
Classifier: License :: OSI Approved :: BSD License
Classifier: Operating System :: POSIX :: Linux
Classifier: Programming Language :: Python :: 3
Classifier: Programming Language :: Python :: 3.4
Requires-Dist: geoip2 (>=2.1.0)
Requires-Dist: maxminddb (>=1.1.1)
Requires-Dist: requests (>=2.5.0)
Requires-Dist: wget (>=2.2)
Requires-Dist: wheel (>=0.24.0)
Requires-Dist: keyring (>=10.4.0)
Requires-Dist: dbus-python (>=1.2.4)
